llm_handler/__init__.py
llm_handler/handler.py
llm_handler-0.1.4.dist-info/LICENSE
llm_handler-0.1.4.dist-info/METADATA
llm_handler-0.1.4.dist-info/WHEEL
llm_handler-0.1.4.dist-info/top_level.txt
llm_handler-0.1.4.dist-info/RECORD
