Metadata-Version: 2.1
Name: llm-handler
Version: 0.1.4
Summary: A unified handler for LLM API calls across OpenAI, Anthropic, and Google
Home-page: https://github.com/yourusername/llm_handler
Author: Dwai Banerjee
Author-email: dwaibanerjee+python@gmail.com
Classifier: Development Status :: 3 - Alpha
Classifier: Intended Audience :: Developers
Classifier: License :: OSI Approved :: MIT License
Classifier: Operating System :: OS Independent
Classifier: Programming Language :: Python :: 3
Classifier: Programming Language :: Python :: 3.7
Classifier: Programming Language :: Python :: 3.8
Classifier: Programming Language :: Python :: 3.9
Classifier: Programming Language :: Python :: 3.10
Requires-Python: >=3.7
License-File: LICENSE
Requires-Dist: openai
Requires-Dist: anthropic
Requires-Dist: google-generativeai
Requires-Dist: python-dotenv
Requires-Dist: tiktoken
